ScEqAn/Analysis.py
ScEqAn-1.0.0.dist-info/LICENSE.txt
ScEqAn-1.0.0.dist-info/METADATA
ScEqAn-1.0.0.dist-info/WHEEL
ScEqAn-1.0.0.dist-info/top_level.txt
ScEqAn-1.0.0.dist-info/RECORD
