Metadata-Version: 2.1
Name: ScEqAn
Version: 1.0.0
Summary: Scientific Equation/Expression Analysis Based On Dynamic Program Analysis
Home-page: https://github.com/Palani-SN/ScEqAn
Author: Palani-SN
Author-email: psn396@gmail.com
License: UNKNOWN
Platform: UNKNOWN
Classifier: Programming Language :: Python :: 3
Classifier: Programming Language :: Python :: 3.7
Classifier: License :: OSI Approved :: GNU General Public License v3 or later (GPLv3+)
Classifier: Operating System :: OS Independent
Requires-Dist: blessings (~=1.7)
Provides-Extra: dev
Requires-Dist: pytest (>=3.7) ; extra == 'dev'
Requires-Dist: check-manifest ; extra == 'dev'
Requires-Dist: twine ; extra == 'dev'
